[{"__type__":"cc.SpriteFrame","content":{"name":"player2","texture":"fdnNlCTSFM6IO2fXopc+sy","rect":[18,13,131,163],"offset":[1,2],"originalSize":[165,193],"capInsets":[0,0,0,0]}},[{"__type__":"cc.SceneAsset","_name":"game","scene":{"__id__":1},"asyncLoadAssets":null},{"__type__":"cc.Scene","_name":"New Node","_children":[{"__id__":2}],"_anchorPoint":{"__type__":"cc.Vec2"},"_trs":{"__type__":"TypedArray","ctor":"Float64Array","array":[0,0,0,0,0,0,1,1,1,1]}},{"__type__":"cc.Node","_name":"Canvas","_parent":{"__id__":1},"_children":[{"__id__":3},{"__id__":4},{"__id__":5}],"_components":[{"__type__":"cc.Canvas","node":{"__id__":2},"_designResolution":{"__type__":"cc.Size","width":640,"height":1035},"_fitWidth":true},{"__type__":"cc.Widget","node":{"__id__":2},"_alignFlags":45}],"_contentSize":{"__type__":"cc.Size","width":640,"height":1035},"_trs":{"__type__":"TypedArray","ctor":"Float64Array","array":[320,517.5,0,0,0,0,1,1,1,1]},"_id":"71LuXJVG5PqLpnS4cNmFmZ"},{"__type__":"cc.Node","_name":"Main Camera","_parent":{"__id__":2},"_components":[{"__type__":"cc.Camera","node":{"__id__":3},"_clearFlags":7,"_depth":-1}],"_trs":{"__type__":"TypedArray","ctor":"Float64Array","array":[0,0,896.3362929168941,0,0,0,1,1,1,1]}},{"__type__":"cc.Node","_name":"background","_parent":{"__id__":2},"_components":[{"__type__":"cc.Sprite","node":{"__id__":4},"_materials":[{"__uuid__":"ecpdLyjvZBwrvm+cedCcQy"}],"_spriteFrame":{"__uuid__":"a4MWeLhgNOraMzO4SH8CT6"}}],"_contentSize":{"__type__":"cc.Size","width":640,"height":1136},"_trs":{"__type__":"TypedArray","ctor":"Float64Array","array":[0,0,0,0,0,0,1,1,1,1]}},{"__type__":"cc.Node","_name":"player","_parent":{"__id__":2},"_components":[{"__type__":"cc.Sprite","node":{"__id__":5},"_materials":[{"__uuid__":"ecpdLyjvZBwrvm+cedCcQy"}],"_spriteFrame":{"__uuid__":"a5imkQcDNK6aXndALZ5yye"}},{"__type__":"cc.Animation","node":{"__id__":5},"_defaultClip":{"__uuid__":"e5UdBr8DxLWpjLplqhKEM2"},"_clips":[{"__uuid__":"e5UdBr8DxLWpjLplqhKEM2"}]},{"__type__":"a5773P4X0VP84W1weo9XbOh","node":{"__id__":5},"air":null}],"_contentSize":{"__type__":"cc.Size","width":131,"height":163},"_trs":{"__type__":"TypedArray","ctor":"Float64Array","array":[0,-400,0,0,0,0,1,1,1,1]}}],{"__type__":"cc.SpriteFrame","content":{"name":"background","texture":"3eqDoOMwpOVKYXbd79a0zb","rect":[0,0,640,1136],"offset":[0,0],"originalSize":[640,1136],"capInsets":[0,0,0,0]}},{"__type__":"cc.SpriteFrame","content":{"name":"player1","texture":"a9pxfxqp1L/JyYReSkQnGR","rect":[18,13,131,163],"offset":[1,2],"originalSize":[165,193],"capInsets":[0,0,0,0]}},{"__type__":"cc.AnimationClip","_name":"player","_duration":0.35,"wrapMode":2,"curveData":{"comps":{"cc.Sprite":{"spriteFrame":[{"frame":0,"value":{"__uuid__":"a5imkQcDNK6aXndALZ5yye"}},{"frame":0.16666666666666666,"value":{"__uuid__":"64jtXEATdHabtm3SThH0Zd"}},{"frame":0.3333333333333333,"value":{"__uuid__":"a5imkQcDNK6aXndALZ5yye"}}]}}}}]